emoji_greeter/__init__.py
emoji_greeter/greet.py
emoji_greeter-0.1.0.dist-info/licenses/LICENSE
emoji_greeter-0.1.0.dist-info/METADATA
emoji_greeter-0.1.0.dist-info/WHEEL
emoji_greeter-0.1.0.dist-info/top_level.txt
emoji_greeter-0.1.0.dist-info/RECORD
