Metadata-Version: 2.4
Name: emoji-greeter
Version: 0.1.0
Summary: A fun greeting package with emojis based on time of day
Author-email: KANAKAM MANOJ <manojkanakam73@gmail.com>
License-Expression: MIT
Requires-Python: >=3.7
License-File: LICENSE
Dynamic: license-file
